sn_graph/__init__.py
sn_graph/core.py
sn_graph/visualisation.py
sn_graph-0.3.0.dist-info/LICENSE
sn_graph-0.3.0.dist-info/METADATA
sn_graph-0.3.0.dist-info/WHEEL
sn_graph-0.3.0.dist-info/RECORD
