Metadata-Version: 2.1
Name: sn-graph
Version: 0.3.0
Summary: A Python implementation of SN-Graph algorithm.
Home-page: https://alexandrainst.github.io/sn-graph
License: MIT
Author: Tomasz Prytula
Author-email: tomasz.prytula@alexandra.dk
Requires-Python: >=3.11,<4.0
Classifier: License :: OSI Approved :: MIT License
Classifier: Programming Language :: Python :: 3
Classifier: Programming Language :: Python :: 3.11
Classifier: Programming Language :: Python :: 3.12
Requires-Dist: matplotlib (>=3.9.3,<4.0.0)
Requires-Dist: numpy (==2.0)
Requires-Dist: scikit-fmm (>=2024.9.16,<2025.0.0)
Requires-Dist: scikit-image (>=0.24.0,<0.25.0)
Requires-Dist: trimesh (>=4.6.8,<5.0.0)
Project-URL: Repository, https://github.com/alexandrainst/sn-graph
